mall/__init__.py
mall/data.py
mall/llm.py
mall/llmvec.py
mall/polars.py
mall/prompt.py
mlverse_mall-0.2.0.dist-info/METADATA
mlverse_mall-0.2.0.dist-info/WHEEL
mlverse_mall-0.2.0.dist-info/RECORD
