Metadata-Version: 2.4
Name: mlverse-mall
Version: 0.2.0
Summary: Run multiple 'Large Language Model' predictions against a table. The predictions run row-wise over a specified column.
Project-URL: homepage, https://mlverse.github.io/mall/
Project-URL: issues, https://github.com/mlverse/mall/issues
Author-email: Edgar Ruiz <edgar@posit.co>
Keywords: large language models,llm,natural language processing,nlp,polars
Classifier: Intended Audience :: Developers
Classifier: Intended Audience :: End Users/Desktop
Classifier: Intended Audience :: Financial and Insurance Industry
Classifier: Intended Audience :: Healthcare Industry
Classifier: Intended Audience :: Science/Research
Classifier: License :: OSI Approved :: MIT License
Classifier: Programming Language :: Python
Classifier: Programming Language :: Python :: 3.9
Classifier: Programming Language :: Python :: 3.10
Classifier: Programming Language :: Python :: 3.11
Classifier: Programming Language :: Python :: 3.12
Classifier: Programming Language :: Python :: 3.13
Classifier: Programming Language :: Python :: Implementation :: PyPy
Classifier: Topic :: Software Development :: Libraries :: Python Modules
Requires-Python: >=3.9
Requires-Dist: chatlas>=0.7.0
Requires-Dist: json5>=0.9.25
Requires-Dist: ollama>=0.3.3
Requires-Dist: openai>=1.77.0
Requires-Dist: polars>=1.9.0
Requires-Dist: pytest-cov>=5.0.0
Requires-Dist: pytest-html>=4.1.1
Requires-Dist: pytest-metadata>=3.1.1
Requires-Dist: pytest>=8.3.3
